smartbudget/__init__.py
smartbudget/analysis_module_1/__init__.py
smartbudget/analysis_module_1/insights.py
smartbudget/analysis_module_1/summary.py
smartbudget/core_module_2/__init__.py
smartbudget/core_module_2/app_menu_controller.py
smartbudget/core_module_2/budget_record_controller.py
smartbudget/core_module_2/file_io_data_controller.py
smartbudget/customized_exception/__init__.py
smartbudget/customized_exception/smartbudget_customize_exception.py
smartbudget/entity/__init__.py
smartbudget/entity/base_record.py
smartbudget/entity/constants.py
smartbudget/entity/expense.py
smartbudget/entity/income.py
smartbudget/file_io_module_3/__init__.py
smartbudget/file_io_module_3/file_utils.py
smartbudget/file_io_module_3/json_io.py
smartbudget_mds533_sun_david-0.1.0.dist-info/METADATA
smartbudget_mds533_sun_david-0.1.0.dist-info/WHEEL
smartbudget_mds533_sun_david-0.1.0.dist-info/top_level.txt
smartbudget_mds533_sun_david-0.1.0.dist-info/RECORD
