Metadata-Version: 2.4
Name: smartbudget-mds533-sun-david
Version: 0.1.0
Summary: SmartBudget: A simple budgeting tool for MDS 533 Step 3 project
Author: Chongwen Sun, Yifu Zhao,Chuying Chen
Author-email: chongwen.sun1992@gmail.com
Classifier: Programming Language :: Python :: 3
Classifier: License :: OSI Approved :: MIT License
Classifier: Operating System :: OS Independent
Requires-Python: >=3.8
Dynamic: author
Dynamic: author-email
Dynamic: classifier
Dynamic: requires-python
Dynamic: summary
